Workbook
Name MisHojas: REPLACE(MIEMBRO.A.M.R(1),1,FIND("]",MIEMBRO.A.M.R(1)),"")

Sheet INICIO
A1: INICIO
A2: Resultados
A3: Graficos
A4: ID lotes
A5: Ingresos por ventas de café
A6: instalacion de café
A7: Control de arvenses
A8: Fertilizacion
A9: Control Fitosanitario
A10: Regulacion de sombrio
A11: Otras labores
A12: Recoleccion
... A18: Presupuesto

Sheet Resultados
A1: RESULTADOS ECONOMICOS DE PRODUCCION DE CAFÉ | G1: INICIO
A2: Ingresos
A3: INGRESOS POR VENTAS DE CAFÉ | D3: =IFERROR(('Ingresos por ventas de cafe'!D20/'ID lotes'!B17)/12.5, 0) | E3: Productividad (@/HA)
A4: VENTAS ($) DE CPS | B4: =+'Ingresos por ventas de cafe'!F20 | D4: =IFERROR(Recoleccion!C20/'Ingresos por ventas de cafe'!D20, 0) | E4: Factor de Conversión
A5: Egresos
A6: ITEM | B6: Total | D6: ITEM | E6: Total | G6: ITEM | H6: Total
A7: Instalación | D7: Control Fitosanitario | G7: Beneficio
A8: MO | B8: =+'Instalacion de Cafe'!F20 | D8: MO | E8: =+'Control Fitosanitario'!F20 | G8: MO | H8: =+Beneficio!E20
A9: Insumos | B9: =+'Instalacion de Cafe'!L20 | D9: Insumos | E9: =+'Control Fitosanitario'!M20 | G9: Sub-total | H9: =+H8
A10: Sub-total | B10: =+B8+B9 | D10: Sub-total | E10: =+E8+E9
A12: Control de Arvenses | D12: Regulación de Sombríos | G12: Administración
A13: MO | B13: =+'Control de arvenses'!F20 | D13: MO | E13: =+'Regulacion de sombrio'!F20 | G13: $/AÑO | H13: =+'Gastos Administrativos'!C20
A14: Insumos | B14: =+'Control de arvenses'!M20 | D14: Insumos | E14: =+'Regulacion de sombrio'!L20 | G14: Sub-total | H14: =+H13
A15: Sub-total | B15: =+B13+B14 | D15: Sub-total | E15: =+E13+E14
G16: Total Egresos | H16: =+B10+B15+B20+E10+E15+E20+H9+H14
A17: Fertilización | D17: Recolección
A18: MO | B18: =+Fertilizacion!F20 | D18: kilos | E18: =+Recoleccion!C20 | G18: Margen | H18: =+B4-H16
A19: Insumos | B19: =+Fertilizacion!L20 | D19: precio | E19: =+Recoleccion!E20
A20: Sub-total | B20: =+B18+B19 | D20: Sub-total | E20: =+E19

Sheet Graficos
A1: Instalacion | B1: =+Resultados!B10 | C1: =+B1/B9 | E1: 10
A2: Control de Arvenses | B2: =+Resultados!B15 | C2: =+B2/B9 | E2: 30
A3: Fertilización | B3: =+Resultados!B20 | C3: =+B3/B9 | E3: 40
A4: Control Fitosanitario | B4: =+Resultados!E10 | C4: =+B4/B9 | E4: 15
A5: Regulación de Sombríos | B5: =+Resultados!E15 | C5: =+B5/B9 | E5: 80
A6: Recolección | B6: =+Resultados!E20 | C6: =+B6/B9 | E6: 66
A7: Beneficio | B7: =+Resultados!H9 | C7: =+B7/B9 | E7: 37
A8: Administración | B8: =+Resultados!H14 | C8: =+B8/B9 | E8: 25
A9: Total | B9: =+SUM(B1:B8) | E9: =+SUM(E1:E8)
A12: INICIO

Sheet ID lotes
A1: ID LOTE | B1: AREA | C1: # ARBOLES | D1: VARIEDAD | E1: FECHA DE LABOR | F1: EDAD (MESES) | H1: INICIO
F2: =IF(E2="", 0, DATEDIF(VALUE(E2), TODAY(), "M"))
F3: =IF(E3="", 0, DATEDIF(VALUE(E3), TODAY(), "M"))
F4: =IF(E4="", 0, DATEDIF(VALUE(E4), TODAY(), "M"))
F5: =IF(E5="", 0, DATEDIF(VALUE(E5), TODAY(), "M"))
F6: =IF(E6="", 0, DATEDIF(VALUE(E6), TODAY(), "M"))
F7: =IF(E7="", 0, DATEDIF(VALUE(E7), TODAY(), "M"))
F8: =IF(E8="", 0, DATEDIF(VALUE(E8), TODAY(), "M"))
F9: =IF(E9="", 0, DATEDIF(VALUE(E9), TODAY(), "M"))
F10: =IF(E10="", 0, DATEDIF(VALUE(E10), TODAY(), "M"))
F11: =IF(E11="", 0, DATEDIF(VALUE(E11), TODAY(), "M"))
F12: =IF(E12="", 0, DATEDIF(VALUE(E12), TODAY(), "M"))
F13: =IF(E13="", 0, DATEDIF(VALUE(E13), TODAY(), "M"))
... F16: =IF(E16="", 0, DATEDIF(VALUE(E16), TODAY(), "M"))
A17: AREA TOTAL | B17: =SUBTOTAL(109,Tabla4[AREA]) | C17: =SUBTOTAL(109,Tabla4['# ARBOLES]) | F17: =SUBTOTAL(101,Tabla4[EDAD (MESES)])

Sheet Ingresos por ventas de cafe
A1: INGRESOS POR VENTAS DE CAFÉ
A2: Fecha | B2: Unidad de venta | C2: Tupo de café | D2: Cantidad | E2: Valor Unitario | F2: Valor total | N2: INICIO
E3: =IFERROR(F3/D3, 0) | K3: kilos | L3: cps
E4: =IFERROR(F4/D4, 0) | I4: 346668 | L4: pasilla
E5: =IFERROR(F5/D5, 0) | G5: 21.68 | I5: =+I4/D3
E6: =IFERROR(F6/D6, 0)
E7: =IFERROR(F7/D7, 0)
E8: =IFERROR(F8/D8, 0)
E9: =IFERROR(F9/D9, 0) | H9: =+D3+D4+D5+D7+D8+D9
E10: =IFERROR(F10/D10, 0) | H10: =+D6+D10 | J10: 220000
E11: =IFERROR(F11/D11, 0) | H11: =+H9+H10 | I11: 872 | J11: =+J10/12.5
E12: =IFERROR(F12/D12, 0) | I12: =+I11/5 | J12: =+J11/4000
E13: =IFERROR(F13/D13, 0)
E14: =IFERROR(F14/D14, 0) | H14: =+F3+F4+F5+F7+F8+F9 | I14: 1416
E15: =IFERROR(F15/D15, 0) | H15: =+F6+F10
E16: =IFERROR(F16/D16, 0)
E17: =IFERROR(F17/D17, 0)
E18: =IFERROR(F18/D18, 0)
E19: =IFERROR(F19/D19, 0) | H19: =+F20*7/100
A20: Total | B20: =+SUM(B3:B19) | D20: =+SUM(D3:D19) | E20: Total | F20: =+SUM(F3:F19)

Sheet Instalacion de Cafe
A1: MANO DE OBRA | H1: INSUMOS
A2: ID LOTES | B2: Fecha | C2: Labor realizada | D2: Número de jornales | E2: Valor unitario | F2: Valor total | G2: INICIO | H2: Fecha | I2: Producto | J2: Cantidad | K2: Valor unitario | L2: Valor Total
F3: =IFERROR(D3*E3, 0) | L3: =IFERROR(+K3*J3, 0)
F4: =IFERROR(D4*E4, 0) | L4: =IFERROR(+K4*J4, 0)
F5: =IFERROR(D5*E5, 0) | L5: =IFERROR(+K5*J5, 0)
F6: =IFERROR(D6*E6, 0) | L6: =IFERROR(+K6*J6, 0)
F7: =IFERROR(D7*E7, 0) | L7: =IFERROR(+K7*J7, 0)
F8: =IFERROR(D8*E8, 0) | L8: =IFERROR(+K8*J8, 0)
F9: =IFERROR(D9*E9, 0) | L9: =IFERROR(+K9*J9, 0)
F10: =IFERROR(D10*E10, 0) | L10: =IFERROR(+K10*J10, 0)
F11: =IFERROR(D11*E11, 0) | L11: =IFERROR(+K11*J11, 0)
F12: =IFERROR(D12*E12, 0) | L12: =IFERROR(+K12*J12, 0)
F13: =IFERROR(D13*E13, 0) | L13: =IFERROR(+K13*J13, 0)
F14: =IFERROR(D14*E14, 0) | L14: =IFERROR(+K14*J14, 0)
... F19: =IFERROR(D19*E19, 0) | L19: =IFERROR(+K19*J19, 0)
E20: Total | F20: =+SUM(F3:F19) | K20: Total | L20: =+SUM(L3:L19)

Sheet Control de arvenses
A1: MANO DE OBRA | H1: INSUMOS
A2: ID LOTES | B2: Fecha | C2: Labor realizada | D2: Número de jornales | E2: Valor Unitario | F2: Valor Total | G2: INICIO | H2: Fecha | I2: Labor realizada | J2: Producto | K2: Cantidad | L2: Valor unitario | M2: Valor Total
F3: =IFERROR(E3*D3, 0) | M3: =IFERROR(+L3*K3, 0) | S3: manual | T3: plateo
F4: =IFERROR(E4*D4, 0) | M4: =IFERROR(+L4*K4, 0) | S4: machete | T4: machete
F5: =IFERROR(E5*D5, 0) | M5: =IFERROR(+L5*K5, 0) | S5: guadaña | T5: mecanico
F6: =IFERROR(E6*D6, 0) | M6: =IFERROR(+L6*K6, 0) | S6: quimico | T6: quimico
F7: =IFERROR(E7*D7, 0) | M7: =IFERROR(+L7*K7, 0)
F8: =IFERROR(E8*D8, 0) | M8: =IFERROR(+L8*K8, 0)
F9: =IFERROR(E9*D9, 0) | M9: =IFERROR(+L9*K9, 0)
F10: =IFERROR(E10*D10, 0) | M10: =IFERROR(+L10*K10, 0)
F11: =IFERROR(E11*D11, 0) | M11: =IFERROR(+L11*K11, 0)
F12: =IFERROR(E12*D12, 0) | M12: =IFERROR(+L12*K12, 0)
F13: =IFERROR(E13*D13, 0) | M13: =IFERROR(+L13*K13, 0)
F14: =IFERROR(E14*D14, 0) | M14: =IFERROR(+L14*K14, 0)
F15: =IFERROR(E15*D15, 0) | M15: =IFERROR(+L15*K15, 0)
F16: =IFERROR(E16*D16, 0) | M16: =IFERROR(+L16*K16, 0)
F17: =IFERROR(E17*D17, 0) | M17: =IFERROR(+L17*K17, 0)
F18: =IFERROR(E18*D18, 0) | M18: =IFERROR(+L18*K18, 0)
F19: =IFERROR(E19*D19, 0) | M19: =IFERROR(+L19*K19, 0)
E20: Total | F20: =+SUM(F3:F19) | L20: Total | M20: =+SUM(M3:M19)

Sheet Fertilizacion
A1: MANO DE OBRA | H1: INSUMOS
A2: ID LOTES | B2: Fecha | C2: Labor realizada | D2: Número de jornales | E2: Valor unitario | F2: Valor total | G2: INICIO | H2: Fecha | I2: Producto | J2: Cantidad | K2: Valor unitario | L2: Valor Total
F3: =+E3*D3 | L3: =IFERROR(+K3*J3, 0)
F4: =+E4*D4 | L4: =IFERROR(+K4*J4, 0)
F5: =+E5*D5 | L5: =IFERROR(+K5*J5, 0)
F6: =+E6*D6 | L6: =IFERROR(+K6*J6, 0)
F7: =+E7*D7 | L7: =IFERROR(+K7*J7, 0)
F8: =+E8*D8 | L8: =IFERROR(+K8*J8, 0)
F9: =+E9*D9 | L9: =IFERROR(+K9*J9, 0)
F10: =+E10*D10 | L10: =IFERROR(+K10*J10, 0)
F11: =+E11*D11 | L11: =IFERROR(+K11*J11, 0)
F12: =+E12*D12 | L12: =IFERROR(+K12*J12, 0)
F13: =+E13*D13 | L13: =IFERROR(+K13*J13, 0)
F14: =+E14*D14 | L14: =IFERROR(+K14*J14, 0)
... F19: =+E19*D19 | L19: =IFERROR(+K19*J19, 0)
E20: Total | F20: =+SUM(F3:F19) | K20: Total | L20: =+SUM(L3:L19)

Sheet Control Fitosanitario
A1: MANO DE OBRA | H1: INSUMOS
A2: ID LOTES | B2: Fecha | C2: Labor realizada | D2: Número de jornales | E2: Valor Unitario | F2: Valor Total | G2: INICIO | H2: Fecha | I2: Labor realizada | J2: Producto | K2: Cantidad | L2: Valor unitario | M2: Valor Total
F3: =IFERROR(E3*D3, 0) | M3: =IFERROR(+L3*K3, 0) | U3: biologico
F4: =IFERROR(E4*D4, 0) | M4: =IFERROR(+L4*K4, 0) | U4: quimico
F5: =IFERROR(E5*D5, 0) | M5: =IFERROR(+L5*K5, 0) | U5: roya
F6: =IFERROR(E6*D6, 0) | M6: =IFERROR(+L6*K6, 0) | U6: otras plagas y/o enfermedades
F7: =IFERROR(E7*D7, 0) | M7: =IFERROR(+L7*K7, 0)
F8: =IFERROR(E8*D8, 0) | M8: =IFERROR(+L8*K8, 0)
F9: =IFERROR(E9*D9, 0) | M9: =IFERROR(+L9*K9, 0)
F10: =IFERROR(E10*D10, 0) | M10: =IFERROR(+L10*K10, 0)
F11: =IFERROR(E11*D11, 0) | M11: =IFERROR(+L11*K11, 0)
F12: =IFERROR(E12*D12, 0) | M12: =IFERROR(+L12*K12, 0)
F13: =IFERROR(E13*D13, 0) | M13: =IFERROR(+L13*K13, 0)
F14: =IFERROR(E14*D14, 0) | M14: =IFERROR(+L14*K14, 0)
F15: =IFERROR(E15*D15, 0) | M15: =IFERROR(+L15*K15, 0)
F16: =IFERROR(E16*D16, 0) | M16: =IFERROR(+L16*K16, 0)
F17: =IFERROR(E17*D17, 0) | M17: =IFERROR(+L17*K17, 0)
F18: =IFERROR(E18*D18, 0) | M18: =IFERROR(+L18*K18, 0)
F19: =IFERROR(E19*D19, 0) | M19: =IFERROR(+L19*K19, 0)
F20: =+SUM(F3:F19) | L20: Total | M20: =+SUM(M3:M19)

Sheet Regulacion de sombrio
A1: MANO DE OBRA | H1: INSUMOS
A2: ID LOTES | B2: Fecha | C2: Labor realizada | D2: Número de jornales | E2: Valor unitario | F2: Valor total | G2: INICIO | H2: Fecha | I2: Producto | J2: Cantidad | K2: Valor unitario | L2: Valor Total
F3: =+E3*D3 | L3: =IFERROR(+K3*J3, 0)
F4: =+E4*D4 | L4: =IFERROR(+K4*J4, 0)
F5: =+E5*D5 | L5: =IFERROR(+K5*J5, 0)
F6: =+E6*D6 | L6: =IFERROR(+K6*J6, 0)
F7: =+E7*D7 | L7: =IFERROR(+K7*J7, 0)
F8: =+E8*D8 | L8: =IFERROR(+K8*J8, 0)
F9: =+E9*D9 | L9: =IFERROR(+K9*J9, 0)
F10: =+E10*D10 | L10: =IFERROR(+K10*J10, 0)
F11: =+E11*D11 | L11: =IFERROR(+K11*J11, 0)
F12: =+E12*D12 | L12: =IFERROR(+K12*J12, 0)
F13: =+E13*D13 | L13: =IFERROR(+K13*J13, 0)
F14: =+E14*D14 | L14: =IFERROR(+K14*J14, 0)
... F19: =+E19*D19 | L19: =IFERROR(+K19*J19, 0)
E20: Total | F20: =+SUM(F3:F19) | K20: Total | L20: =+SUM(L3:L19)

Sheet Otras Labores
A1: MANO DE OBRA | H1: INSUMOS
A2: ID LOTES | B2: Fecha | C2: Labor realizada | D2: Número de jornales | E2: Valor unitario | F2: Valor total | G2: INICIO | H2: Fecha | I2: Producto | J2: Cantidad | K2: Valor unitario | L2: Valor Total
F3: =+E3*D3 | L3: =IFERROR(+K3*J3, 0)
F4: =+E4*D4 | L4: =IFERROR(+K4*J4, 0)
F5: =+E5*D5 | L5: =IFERROR(+K5*J5, 0)
F6: =+E6*D6 | L6: =IFERROR(+K6*J6, 0)
F7: =+E7*D7 | L7: =IFERROR(+K7*J7, 0)
F8: =+E8*D8 | L8: =IFERROR(+K8*J8, 0)
F9: =+E9*D9 | L9: =IFERROR(+K9*J9, 0)
F10: =+E10*D10 | L10: =IFERROR(+K10*J10, 0)
F11: =+E11*D11 | L11: =IFERROR(+K11*J11, 0)
F12: =+E12*D12 | L12: =IFERROR(+K12*J12, 0)
F13: =+E13*D13 | L13: =IFERROR(+K13*J13, 0)
F14: =+E14*D14 | L14: =IFERROR(+K14*J14, 0)
... F19: =+E19*D19 | L19: =IFERROR(+K19*J19, 0)
E20: Total | F20: =+SUM(F3:F19) | K20: Total | L20: =+SUM(L3:L19)

Sheet Recoleccion
A1: MANO DE OBRA | F1: INICIO
A2: Fecha | B2: Recolección cereza | C2: Kilos | D2: Valor Unitario | E2: Valor Total
D3: =IFERROR(E3/C3, 0) | N3: RE-RE
D4: =IFERROR(E4/C4, 0) | N4: JORNAL
D5: =IFERROR(E5/C5, 0) | N5: KILO
D6: =IFERROR(E6/C6, 0)
D7: =IFERROR(E7/C7, 0)
D8: =IFERROR(E8/C8, 0)
D9: =IFERROR(E9/C9, 0)
D10: =IFERROR(E10/C10, 0)
D11: =IFERROR(E11/C11, 0)
D12: =IFERROR(E12/C12, 0)
D13: =IFERROR(E13/C13, 0)
D14: =IFERROR(E14/C14, 0)
D15: =IFERROR(E15/C15, 0)
D16: =IFERROR(E16/C16, 0)
D17: =IFERROR(E17/C17, 0)
... D19: =IFERROR(E19/C19, 0)
B20: Total | C20: =+SUM(C3:C19) | D20: Total | E20: =+SUM(E3:E19)

Sheet Beneficio
A1: MANO DE OBRA
A2: Fecha | B2: Labor realizada | C2: Número de jornales | D2: Valor unitario | E2: Valor total | F2: INICIO
E3: =IFERROR(D3*C3, 0)
E4: =IFERROR(D4*C4, 0)
E5: =IFERROR(D5*C5, 0)
E6: =IFERROR(D6*C6, 0)
E7: =IFERROR(D7*C7, 0)
E8: =IFERROR(D8*C8, 0)
E9: =IFERROR(D9*C9, 0)
E10: =IFERROR(D10*C10, 0)
E11: =IFERROR(D11*C11, 0)
E12: =IFERROR(D12*C12, 0)
E13: =IFERROR(D13*C13, 0)
E14: =IFERROR(D14*C14, 0)
... E19: =IFERROR(D19*C19, 0)
D20: Total | E20: =+SUM(E3:E19)

Sheet Gastos Administrativos
A1: Gasto | D1: INICIO
A2: Fecha | B2: Gasto administrativo | C2: Valor total
I3: Servicios Públicos
I4: Impuesto predial
I5: Mantenimiento Infraestructura productiva
I6: Mantenimiento de construcciones
I7: Mantenimiento de vías internas
I8: Herramientas
I9: Transporte de café
I10: Gastos de mantenimiento de vehículos (usados para transporte de café y/o insumos)
I11: Depreciación de construcciones y equipos
I12: Mayordomo
I13: Administrador
I14: Patrón de corte
... I18: Pago de intereses de créditos
B20: Total | C20: =+SUM(C3:C19)

Sheet Plan de ordenamiento

Sheet Plan de acción
A1: INICIO

Sheet Cronograma
A1: INICIO

Sheet Presupuesto
A1: INICIO
